<?xml version="1.0"?>
<categories>
  <category name="backgrounds" display_name="Backgrounds" image="backgrounds.png" columns="5" mode="directory" path="nautilus/backgrounds" type="property/bgimage" description="Drag a background tile to an object to change it"/>
  <category name="emblems" display_name="Emblems" image="emblems.png" columns="6" mode="directory" path="nautilus/emblems" type="property/keyword"  description="Drag an emblem to an object to add it to the object"/>
  <category name="colors" display_name="Colors" image="colors.png" columns="5" mode="inline" type="application/x-color" description="Drag a color to an object to change it to that color">
    <color>rgb:FFFF/FFFF/3333</color>
    <color>rgb:FFFF/CCCC/3333</color>
    <color>rgb:FFFF/9999/3333</color>
    <color>rgb:FFFF/6666/3333</color>
    <color>rgb:FFFF/3333/3333</color>
    <color>rgb:FFFF/0000/3333</color>
    <color>rgb:6666/FFFF/FFFF</color>
    <color>rgb:6666/CCCC/FFFF</color>
    <color>rgb:6666/9999/FFFF</color>
    <color>rgb:6666/6666/FFFF</color>
    <color>rgb:6666/3333/FFFF</color>   
    <color>rgb:0000/3333/CCCC</color>
    <color>rgb:CCCC/FFFF/CCCC</color>
    <color>rgb:9999/FFFF/6666</color>
    <color>rgb:6666/CCCC/6666</color>
    <color>rgb:3333/6666/6666</color>
    <color>rgb:3333/6666/3333</color>   
    <color>rgb:0000/0000/3333</color>
    <color>rgb:0000/0000/0000</color>
    <color>rgb:3333/3333/3333</color>
    <color>rgb:6666/6666/6666</color>
    <color>rgb:9999/9999/9999</color>
    <color>rgb:CCCC/CCCC/CCCC</color>   
    <color>rgb:FFFE/FFFE/FFFE</color>
  </category>
  <category name="Themes" display_name="Themes" image="themes.png" columns="3" mode="themes" path="icons" type="property/theme"  description="Click on a theme button to switch to that theme"/>
</categories>
